StreamJSME/__init__.py
StreamJSME/_version.py
StreamJSME/app.py
StreamJSME/static/index.css
StreamJSME/static/index.html
StreamJSME/static/manifest.json
StreamJSME/static/assets/index-DT9W1wx4.js
streamjsme-0.1.0.dist-info/licenses/LICENSE
streamjsme-0.1.0.dist-info/METADATA
streamjsme-0.1.0.dist-info/WHEEL
streamjsme-0.1.0.dist-info/top_level.txt
streamjsme-0.1.0.dist-info/RECORD
