Metadata-Version: 2.4
Name: StreamJSME
Version: 0.1.0
Summary: StreamJSME is a Streamlit component that use JSME to draw 2D molecules and use them on your Streamlit app
Author-email: Alejandro Martínez León <ale94mleon@gmail.com>
Project-URL: Hompage, https://github.com/ale94mleon/StreamJSME
Project-URL: Discussions, https://github.com/ale94mleon/StreamJSME/discussions
Project-URL: Documentation, https://github.com/ale94mleon/StreamJSME
Project-URL: Issues, https://github.com/ale94mleon/StreamJSME/issues
Keywords: science,chemistry,biology,drug-design
Classifier: Development Status :: 2 - Pre-Alpha
Classifier: Operating System :: OS Independent
Classifier: Intended Audience :: Science/Research
Classifier: Programming Language :: Python :: 3
Classifier: Topic :: Scientific/Engineering :: Bio-Informatics
Classifier: Topic :: Scientific/Engineering :: Chemistry
Requires-Python: >=3.8
License-File: LICENSE
Requires-Dist: streamlit>=0.63
Dynamic: license-file
